banana/__init__.py
banana/benchmark/__init__.py
banana/benchmark/external/__init__.py
banana/benchmark/external/apfel_utils.py
banana/benchmark/external/apfel_xgrid.yaml
banana/benchmark/runner.py
banana/cfg.py
banana/data/.gitignore
banana/data/__init__.py
banana/data/db.py
banana/data/dfdict.py
banana/data/sql.py
banana/data/theories.py
banana/data/theory_template.yaml
banana/navigator/__init__.py
banana/navigator/navigator.py
banana/navigator/table_manager.py
banana/navigator/utils.py
banana/toy.py
banana/utils.py
banana_hep-0.6.17.dist-info/METADATA
banana_hep-0.6.17.dist-info/WHEEL
banana_hep-0.6.17.dist-info/licenses/LICENSE
banana_hep-0.6.17.dist-info/RECORD
