Metadata-Version: 2.4
Name: banana-hep
Version: 0.6.17
Summary: Benchmark QCD physics
License-File: LICENSE
Author: Andrea Barontini
Author-email: andrea.barontini@mi.infn.it
Requires-Python: >=3.9,<4.0
Classifier: Programming Language :: Python
Classifier: Programming Language :: Python :: 3
Classifier: Programming Language :: Python :: 3.9
Classifier: Programming Language :: Python :: 3.10
Classifier: Programming Language :: Python :: 3.11
Classifier: Programming Language :: Python :: 3.12
Classifier: Programming Language :: Python :: 3.13
Classifier: Programming Language :: Python :: 3.14
Classifier: Topic :: Scientific/Engineering
Classifier: Topic :: Scientific/Engineering :: Physics
Requires-Dist: PyYAML (>=6.0,<7.0)
Requires-Dist: SQLAlchemy (>=1.4.29,<2.0.0)
Requires-Dist: appdirs (>=1.4.4,<2.0.0)
Requires-Dist: click (>=8.0.3,<9.0.0)
Requires-Dist: ipython (>=8.1.0,<9.0.0)
Requires-Dist: matplotlib (>=3.5.1,<4.0.0)
Requires-Dist: numpy (>=1.26)
Requires-Dist: pandas (>=2.1.4,<3.0.0)
Requires-Dist: pendulum (>=3.0.0,<4.0.0)
Requires-Dist: rich (>=12.4.4,<13.0.0)
Project-URL: Repository, https://github.com/N3PDF/banana
